cowarp/__init__.py
cowarp/cow_dynamic_no_edges.py
cowarp/warp.py
cowarp-0.1.5.dist-info/licenses/LICENSE
cowarp-0.1.5.dist-info/METADATA
cowarp-0.1.5.dist-info/WHEEL
cowarp-0.1.5.dist-info/top_level.txt
cowarp-0.1.5.dist-info/RECORD
