Metadata-Version: 2.4
Name: cowarp
Version: 0.1.5
Summary: Correlation Optimized Warping (COW) algorithm for signal alignment
Author-email: Guram Chaganava <guram58chaganava@gmail.com>
License-Expression: MIT
Project-URL: Homepage, https://github.com/G93-7/Cowarp
Project-URL: Documentation, https://github.com/G93-7/Cowarp#readme
Keywords: signal processing,time series,warping,alignment,COW
Requires-Python: >=3.8
License-File: LICENSE
Requires-Dist: numpy>=1.20
Dynamic: license-file
